source_bigcommerce/__init__.py
source_bigcommerce/components.py
source_bigcommerce/manifest.yaml
source_bigcommerce/run.py
source_bigcommerce/schemas/brands.json
source_bigcommerce/schemas/categories.json
source_bigcommerce/schemas/channels.json
source_bigcommerce/schemas/customers.json
source_bigcommerce/schemas/order_products.json
source_bigcommerce/schemas/orders.json
source_bigcommerce/schemas/pages.json
source_bigcommerce/schemas/products.json
source_bigcommerce/schemas/shared/meta.json
source_bigcommerce/schemas/store.json
source_bigcommerce/schemas/transactions.json
source_bigcommerce/source.py
airbyte_source_bigcommerce-0.2.22.dist-info/METADATA
airbyte_source_bigcommerce-0.2.22.dist-info/WHEEL
airbyte_source_bigcommerce-0.2.22.dist-info/entry_points.txt
airbyte_source_bigcommerce-0.2.22.dist-info/RECORD
